{
    "61": {
        "AC": "SP",
        "AL": "SP",
        "AM": "SP",
        "AP": "SP",
        "BA": "SP",
        "CE": "SP",
        "DF": "SP",
        "ES": "SP",
        "GO": "SP",
        "MA": "SP",
        "MG": "SP",
        "MS": "SP",
        "MT": "SP",
        "PA": "SP",
        "PB": "SP",
        "PE": "SP",
        "PI": "SP",
        "PR": "SP",
        "RJ": "SP",
        "RN": "SP",
        "RO": "SP",
        "RR": "SP",
        "RS": "SP",
        "SC": "SP",
        "SE": "SP",
        "SP": "SP",
        "TO": "SP"
    }
}